synthnn/__init__.py
synthnn/base.py
synthnn-1.1.5.dist-info/licenses/LICENSE
synthnn-1.1.5.dist-info/METADATA
synthnn-1.1.5.dist-info/WHEEL
synthnn-1.1.5.dist-info/top_level.txt
synthnn-1.1.5.dist-info/RECORD
