Metadata-Version: 2.4
Name: synthnn
Version: 1.1.5
Summary: A Python package implementing the synthetic nearest neighbors estimator for panel data causal inference.
Author-email: Rivka Lipkovitz <rivkal@mit.edu>
License: MIT License
Project-URL: Homepage, https://github.com/rivkalipko/synthnn
Project-URL: Bug Tracker, https://github.com/rivkalipko/synthnn/issues
Classifier: Programming Language :: Python :: 3
Classifier: Programming Language :: Python :: 3.9
Classifier: Programming Language :: Python :: 3.10
Classifier: Programming Language :: Python :: 3.11
Classifier: License :: OSI Approved :: MIT License
Classifier: Operating System :: OS Independent
Classifier: Intended Audience :: Science/Research
Classifier: Topic :: Scientific/Engineering
Requires-Python: >=3.9
License-File: LICENSE
Requires-Dist: numpy>=1.21
Requires-Dist: pandas>=1.3
Requires-Dist: scipy>=1.7
Requires-Dist: plotly>=4.0.0
Requires-Dist: scikit-learn>=1.0
Dynamic: license-file
